MANIFEST.in
README.rst
setup.py
emp_ide/__init__.py
emp_ide/ide.py
emp_ide.egg-info/PKG-INFO
emp_ide.egg-info/SOURCES.txt
emp_ide.egg-info/dependency_links.txt
emp_ide.egg-info/entry_points.txt
emp_ide.egg-info/requires.txt
emp_ide.egg-info/top_level.txt
emp_ide/static/index.html
emp_ide/static/css/app.39efe745.css
emp_ide/static/css/chunk-ba848ce4.b8e159bb.css
emp_ide/static/css/chunk-vendors.be25d2a2.css
emp_ide/static/fonts/MaterialIcons-Regular.012cf6a1.woff
emp_ide/static/fonts/MaterialIcons-Regular.570eb838.woff2
emp_ide/static/fonts/MaterialIcons-Regular.a37b0c01.ttf
emp_ide/static/fonts/MaterialIcons-Regular.e79bfd88.eot
emp_ide/static/img/iconfont.573255ce.svg
emp_ide/static/js/app.6683def7.js
emp_ide/static/js/app.6683def7.js.map
emp_ide/static/js/chunk-2d0a3577.307d1ec2.js
emp_ide/static/js/chunk-2d0a3577.307d1ec2.js.map
emp_ide/static/js/chunk-2d0a43df.4291d641.js
emp_ide/static/js/chunk-2d0a43df.4291d641.js.map
emp_ide/static/js/chunk-2d0aab07.bb9e7df5.js
emp_ide/static/js/chunk-2d0aab07.bb9e7df5.js.map
emp_ide/static/js/chunk-2d0abc00.9574a6fc.js
emp_ide/static/js/chunk-2d0abc00.9574a6fc.js.map
emp_ide/static/js/chunk-2d0ae937.038ae7eb.js
emp_ide/static/js/chunk-2d0ae937.038ae7eb.js.map
emp_ide/static/js/chunk-2d0aeb45.ec0b6c1a.js
emp_ide/static/js/chunk-2d0aeb45.ec0b6c1a.js.map
emp_ide/static/js/chunk-2d0afa49.e4e2a372.js
emp_ide/static/js/chunk-2d0afa49.e4e2a372.js.map
emp_ide/static/js/chunk-2d0b2762.3dba65e0.js
emp_ide/static/js/chunk-2d0b2762.3dba65e0.js.map
emp_ide/static/js/chunk-2d0b6187.b37e250d.js
emp_ide/static/js/chunk-2d0b6187.b37e250d.js.map
emp_ide/static/js/chunk-2d0ba136.0374318d.js
emp_ide/static/js/chunk-2d0ba136.0374318d.js.map
emp_ide/static/js/chunk-2d0bb267.ff4a2b54.js
emp_ide/static/js/chunk-2d0bb267.ff4a2b54.js.map
emp_ide/static/js/chunk-2d0bcec1.898d6826.js
emp_ide/static/js/chunk-2d0bcec1.898d6826.js.map
emp_ide/static/js/chunk-2d0bff92.08053fe8.js
emp_ide/static/js/chunk-2d0bff92.08053fe8.js.map
emp_ide/static/js/chunk-2d0c0494.7bf17059.js
emp_ide/static/js/chunk-2d0c0494.7bf17059.js.map
emp_ide/static/js/chunk-2d0c0a09.a6c7ced0.js
emp_ide/static/js/chunk-2d0c0a09.a6c7ced0.js.map
